{
    "metadata": {
        "version": 4.5,
        "type": "Object",
        "generator": "gs-json"
    },
    "geometries": [
        {
            "uuid": "a705b613-3f59-48da-8255-5085a5e7a495",
            "type": "BufferGeometry",
            "data": {
                "attributes": {
                    "position": {
                        "itemSize": 3,
                        "type": "Float32Array",
                        "array": [
                            0,
                            0,
                            0,
                            10,
                            0,
                            0,
                            10,
                            10,
                            0,
                            0,
                            10,
                            0,
                            0,
                            0,
                            10,
                            10,
                            0,
                            10,
                            10,
                            10,
                            10,
                            0,
                            10,
                            10
                        ],
                        "normalized": false
                    }
                },
                "index": {
                    "type": "Uint16Array",
                    "array": [
                        2,
                        3,
                        0,
                        0,
                        1,
                        2,
                        5,
                        1,
                        0,
                        0,
                        4,
                        5,
                        6,
                        2,
                        1,
                        1,
                        5,
                        6,
                        7,
                        3,
                        2,
                        2,
                        6,
                        7,
                        4,
                        0,
                        3,
                        3,
                        7,
                        4,
                        5,
                        4,
                        7,
                        7,
                        6,
                        5
                    ]
                }
            }
        },
        {
            "uuid": "fadc5e6d-a59b-4c73-a335-e0f787e99866",
            "type": "BufferGeometry",
            "data": {
                "attributes": {
                    "position": {
                        "itemSize": 3,
                        "type": "Float32Array",
                        "array": [
                            0,
                            0,
                            0,
                            10,
                            0,
                            0,
                            10,
                            0,
                            0,
                            10,
                            10,
                            0,
                            10,
                            10,
                            0,
                            0,
                            10,
                            0,
                            0,
                            10,
                            0,
                            0,
                            0,
                            0,
                            0,
                            0,
                            0,
                            0,
                            0,
                            10,
                            0,
                            0,
                            10,
                            10,
                            0,
                            10,
                            10,
                            0,
                            10,
                            10,
                            0,
                            0,
                            10,
                            0,
                            10,
                            10,
                            10,
                            10,
                            10,
                            10,
                            10,
                            10,
                            10,
                            0,
                            10,
                            10,
                            10,
                            0,
                            10,
                            10,
                            0,
                            10,
                            10,
                            0,
                            10,
                            0,
                            0,
                            10,
                            10,
                            0,
                            0,
                            10
                        ],
                        "normalized": false
                    }
                }
            }
        }
    ],
    "materials": [
        {
            "uuid": "e92ce69b-526a-45f4-8a78-86743c57f442",
            "type": "LineBasicMaterial",
            "color": 0,
            "vertexColors": 0,
            "side": 2,
            "blending": 0,
            "depthFunc": 3,
            "depthTest": true,
            "depthWrite": true
        },
        {
            "uuid": "fddcc33c-e241-4e99-8425-8ac59cfcb379",
            "type": "LineBasicMaterial",
            "color": 255,
            "vertexColors": 0,
            "side": 2,
            "blending": 0,
            "depthFunc": 3,
            "depthTest": true,
            "depthWrite": true
        },
        {
            "uuid": "293942c3-8373-4bd7-9c95-2f8a13dc9cbf",
            "type": "MeshPhongMaterial",
            "color": 16777215,
            "emissive": 0,
            "specular": 16777215,
            "shininess": 10,
            "vertexColors": 0,
            "side": 2,
            "blending": 0,
            "depthFunc": 3,
            "depthTest": true,
            "depthWrite": true,
            "transparent": false,
            "wireframe": false,
            "flatShading": true
        },
        {
            "uuid": "ba149a6c-922d-47a3-8f77-bae82fe08359",
            "type": "MeshPhongMaterial",
            "color": 0,
            "emissive": 0,
            "specular": 16777215,
            "shininess": 40,
            "vertexColors": 0,
            "side": 1,
            "blending": 0,
            "depthFunc": 3,
            "depthTest": true,
            "depthWrite": true,
            "transparent": true,
            "opacity": 0.5,
            "wireframe": false,
            "flatShading": true
        }
    ],
    "object": {
        "type": "Scene",
        "name": "Scene",
        "children": [
            {
                "uuid": "ec8e2468-38df-45bf-979d-4e284312b72e",
                "type": "Group",
                "name": "0_Polymesh",
                "children": [
                    {
                        "uuid": "bde0f4ca-aa9c-4872-9d84-a2d7dcacfbfe",
                        "type": "Mesh",
                        "name": "Polymesh Faces",
                        "geometry": "a705b613-3f59-48da-8255-5085a5e7a495",
                        "material": "293942c3-8373-4bd7-9c95-2f8a13dc9cbf",
                        "castShadow": true,
                        "receiveShadow": true
                    },
                    {
                        "uuid": "381e881c-a050-4c76-aa17-d38f037f4206",
                        "type": "LineSegments",
                        "name": "Polymesh Face Edges",
                        "geometry": "fadc5e6d-a59b-4c73-a335-e0f787e99866",
                        "material": "e92ce69b-526a-45f4-8a78-86743c57f442",
                        "castShadow": false,
                        "receiveShadow": false
                    },
                    {
                        "uuid": "a4101ce9-779f-47ed-8c55-b6a370eb01ac",
                        "type": "Group",
                        "name": "Vertices",
                        "children": [
                            {
                                "type": "Sprite",
                                "name": "o0:f0:v0",
                                "matrix": [
                                    1,
                                    0,
                                    0,
                                    0,
                                    0,
                                    1,
                                    0,
                                    0,
                                    0,
                                    0,
                                    1,
                                    0,
                                    0,
                                    0,
                                    0,
                                    1
                                ],
                                "visible": false
                            },
                            {
                                "type": "Sprite",
                                "name": "o0:f0:v1",
                                "matrix": [
                                    1,
                                    0,
                                    0,
                                    0,
                                    0,
                                    1,
                                    0,
                                    0,
                                    0,
                                    0,
                                    1,
                                    0,
                                    10,
                                    0,
                                    0,
                                    1
                                ],
                                "visible": false
                            },
                            {
                                "type": "Sprite",
                                "name": "o0:f0:v2",
                                "matrix": [
                                    1,
                                    0,
                                    0,
                                    0,
                                    0,
                                    1,
                                    0,
                                    0,
                                    0,
                                    0,
                                    1,
                                    0,
                                    10,
                                    10,
                                    0,
                                    1
                                ],
                                "visible": false
                            },
                            {
                                "type": "Sprite",
                                "name": "o0:f0:v3",
                                "matrix": [
                                    1,
                                    0,
                                    0,
                                    0,
                                    0,
                                    1,
                                    0,
                                    0,
                                    0,
                                    0,
                                    1,
                                    0,
                                    0,
                                    10,
                                    0,
                                    1
                                ],
                                "visible": false
                            },
                            {
                                "type": "Sprite",
                                "name": "o0:f1:v0",
                                "matrix": [
                                    1,
                                    0,
                                    0,
                                    0,
                                    0,
                                    1,
                                    0,
                                    0,
                                    0,
                                    0,
                                    1,
                                    0,
                                    0,
                                    0,
                                    0,
                                    1
                                ],
                                "visible": false
                            },
                            {
                                "type": "Sprite",
                                "name": "o0:f1:v1",
                                "matrix": [
                                    1,
                                    0,
                                    0,
                                    0,
                                    0,
                                    1,
                                    0,
                                    0,
                                    0,
                                    0,
                                    1,
                                    0,
                                    0,
                                    0,
                                    10,
                                    1
                                ],
                                "visible": false
                            },
                            {
                                "type": "Sprite",
                                "name": "o0:f1:v2",
                                "matrix": [
                                    1,
                                    0,
                                    0,
                                    0,
                                    0,
                                    1,
                                    0,
                                    0,
                                    0,
                                    0,
                                    1,
                                    0,
                                    10,
                                    0,
                                    10,
                                    1
                                ],
                                "visible": false
                            },
                            {
                                "type": "Sprite",
                                "name": "o0:f1:v3",
                                "matrix": [
                                    1,
                                    0,
                                    0,
                                    0,
                                    0,
                                    1,
                                    0,
                                    0,
                                    0,
                                    0,
                                    1,
                                    0,
                                    10,
                                    0,
                                    0,
                                    1
                                ],
                                "visible": false
                            },
                            {
                                "type": "Sprite",
                                "name": "o0:f2:v0",
                                "matrix": [
                                    1,
                                    0,
                                    0,
                                    0,
                                    0,
                                    1,
                                    0,
                                    0,
                                    0,
                                    0,
                                    1,
                                    0,
                                    10,
                                    0,
                                    0,
                                    1
                                ],
                                "visible": false
                            },
                            {
                                "type": "Sprite",
                                "name": "o0:f2:v1",
                                "matrix": [
                                    1,
                                    0,
                                    0,
                                    0,
                                    0,
                                    1,
                                    0,
                                    0,
                                    0,
                                    0,
                                    1,
                                    0,
                                    10,
                                    0,
                                    10,
                                    1
                                ],
                                "visible": false
                            },
                            {
                                "type": "Sprite",
                                "name": "o0:f2:v2",
                                "matrix": [
                                    1,
                                    0,
                                    0,
                                    0,
                                    0,
                                    1,
                                    0,
                                    0,
                                    0,
                                    0,
                                    1,
                                    0,
                                    10,
                                    10,
                                    10,
                                    1
                                ],
                                "visible": false
                            },
                            {
                                "type": "Sprite",
                                "name": "o0:f2:v3",
                                "matrix": [
                                    1,
                                    0,
                                    0,
                                    0,
                                    0,
                                    1,
                                    0,
                                    0,
                                    0,
                                    0,
                                    1,
                                    0,
                                    10,
                                    10,
                                    0,
                                    1
                                ],
                                "visible": false
                            },
                            {
                                "type": "Sprite",
                                "name": "o0:f3:v0",
                                "matrix": [
                                    1,
                                    0,
                                    0,
                                    0,
                                    0,
                                    1,
                                    0,
                                    0,
                                    0,
                                    0,
                                    1,
                                    0,
                                    10,
                                    10,
                                    0,
                                    1
                                ],
                                "visible": false
                            },
                            {
                                "type": "Sprite",
                                "name": "o0:f3:v1",
                                "matrix": [
                                    1,
                                    0,
                                    0,
                                    0,
                                    0,
                                    1,
                                    0,
                                    0,
                                    0,
                                    0,
                                    1,
                                    0,
                                    10,
                                    10,
                                    10,
                                    1
                                ],
                                "visible": false
                            },
                            {
                                "type": "Sprite",
                                "name": "o0:f3:v2",
                                "matrix": [
                                    1,
                                    0,
                                    0,
                                    0,
                                    0,
                                    1,
                                    0,
                                    0,
                                    0,
                                    0,
                                    1,
                                    0,
                                    0,
                                    10,
                                    10,
                                    1
                                ],
                                "visible": false
                            },
                            {
                                "type": "Sprite",
                                "name": "o0:f3:v3",
                                "matrix": [
                                    1,
                                    0,
                                    0,
                                    0,
                                    0,
                                    1,
                                    0,
                                    0,
                                    0,
                                    0,
                                    1,
                                    0,
                                    0,
                                    10,
                                    0,
                                    1
                                ],
                                "visible": false
                            },
                            {
                                "type": "Sprite",
                                "name": "o0:f4:v0",
                                "matrix": [
                                    1,
                                    0,
                                    0,
                                    0,
                                    0,
                                    1,
                                    0,
                                    0,
                                    0,
                                    0,
                                    1,
                                    0,
                                    0,
                                    10,
                                    0,
                                    1
                                ],
                                "visible": false
                            },
                            {
                                "type": "Sprite",
                                "name": "o0:f4:v1",
                                "matrix": [
                                    1,
                                    0,
                                    0,
                                    0,
                                    0,
                                    1,
                                    0,
                                    0,
                                    0,
                                    0,
                                    1,
                                    0,
                                    0,
                                    10,
                                    10,
                                    1
                                ],
                                "visible": false
                            },
                            {
                                "type": "Sprite",
                                "name": "o0:f4:v2",
                                "matrix": [
                                    1,
                                    0,
                                    0,
                                    0,
                                    0,
                                    1,
                                    0,
                                    0,
                                    0,
                                    0,
                                    1,
                                    0,
                                    0,
                                    0,
                                    10,
                                    1
                                ],
                                "visible": false
                            },
                            {
                                "type": "Sprite",
                                "name": "o0:f4:v3",
                                "matrix": [
                                    1,
                                    0,
                                    0,
                                    0,
                                    0,
                                    1,
                                    0,
                                    0,
                                    0,
                                    0,
                                    1,
                                    0,
                                    0,
                                    0,
                                    0,
                                    1
                                ],
                                "visible": false
                            },
                            {
                                "type": "Sprite",
                                "name": "o0:f5:v0",
                                "matrix": [
                                    1,
                                    0,
                                    0,
                                    0,
                                    0,
                                    1,
                                    0,
                                    0,
                                    0,
                                    0,
                                    1,
                                    0,
                                    0,
                                    10,
                                    10,
                                    1
                                ],
                                "visible": false
                            },
                            {
                                "type": "Sprite",
                                "name": "o0:f5:v1",
                                "matrix": [
                                    1,
                                    0,
                                    0,
                                    0,
                                    0,
                                    1,
                                    0,
                                    0,
                                    0,
                                    0,
                                    1,
                                    0,
                                    10,
                                    10,
                                    10,
                                    1
                                ],
                                "visible": false
                            },
                            {
                                "type": "Sprite",
                                "name": "o0:f5:v2",
                                "matrix": [
                                    1,
                                    0,
                                    0,
                                    0,
                                    0,
                                    1,
                                    0,
                                    0,
                                    0,
                                    0,
                                    1,
                                    0,
                                    10,
                                    0,
                                    10,
                                    1
                                ],
                                "visible": false
                            },
                            {
                                "type": "Sprite",
                                "name": "o0:f5:v3",
                                "matrix": [
                                    1,
                                    0,
                                    0,
                                    0,
                                    0,
                                    1,
                                    0,
                                    0,
                                    0,
                                    0,
                                    1,
                                    0,
                                    0,
                                    0,
                                    10,
                                    1
                                ],
                                "visible": false
                            }
                        ]
                    },
                    {
                        "uuid": "80494080-70f2-43f9-9de6-21f6fe78c465",
                        "type": "Group",
                        "name": "Edges",
                        "children": [
                            {
                                "type": "Sprite",
                                "name": "o0:f0:e0",
                                "matrix": [
                                    1,
                                    0,
                                    0,
                                    0,
                                    0,
                                    1,
                                    0,
                                    0,
                                    0,
                                    0,
                                    1,
                                    0,
                                    5,
                                    0,
                                    0,
                                    1
                                ],
                                "visible": false
                            },
                            {
                                "type": "Sprite",
                                "name": "o0:f0:e1",
                                "matrix": [
                                    1,
                                    0,
                                    0,
                                    0,
                                    0,
                                    1,
                                    0,
                                    0,
                                    0,
                                    0,
                                    1,
                                    0,
                                    10,
                                    5,
                                    0,
                                    1
                                ],
                                "visible": false
                            },
                            {
                                "type": "Sprite",
                                "name": "o0:f0:e2",
                                "matrix": [
                                    1,
                                    0,
                                    0,
                                    0,
                                    0,
                                    1,
                                    0,
                                    0,
                                    0,
                                    0,
                                    1,
                                    0,
                                    5,
                                    10,
                                    0,
                                    1
                                ],
                                "visible": false
                            },
                            {
                                "type": "Sprite",
                                "name": "o0:f0:e3",
                                "matrix": [
                                    1,
                                    0,
                                    0,
                                    0,
                                    0,
                                    1,
                                    0,
                                    0,
                                    0,
                                    0,
                                    1,
                                    0,
                                    0,
                                    5,
                                    0,
                                    1
                                ],
                                "visible": false
                            },
                            {
                                "type": "Sprite",
                                "name": "o0:f1:e0",
                                "matrix": [
                                    1,
                                    0,
                                    0,
                                    0,
                                    0,
                                    1,
                                    0,
                                    0,
                                    0,
                                    0,
                                    1,
                                    0,
                                    0,
                                    0,
                                    5,
                                    1
                                ],
                                "visible": false
                            },
                            {
                                "type": "Sprite",
                                "name": "o0:f1:e1",
                                "matrix": [
                                    1,
                                    0,
                                    0,
                                    0,
                                    0,
                                    1,
                                    0,
                                    0,
                                    0,
                                    0,
                                    1,
                                    0,
                                    5,
                                    0,
                                    10,
                                    1
                                ],
                                "visible": false
                            },
                            {
                                "type": "Sprite",
                                "name": "o0:f1:e2",
                                "matrix": [
                                    1,
                                    0,
                                    0,
                                    0,
                                    0,
                                    1,
                                    0,
                                    0,
                                    0,
                                    0,
                                    1,
                                    0,
                                    10,
                                    0,
                                    5,
                                    1
                                ],
                                "visible": false
                            },
                            {
                                "type": "Sprite",
                                "name": "o0:f1:e3",
                                "matrix": [
                                    1,
                                    0,
                                    0,
                                    0,
                                    0,
                                    1,
                                    0,
                                    0,
                                    0,
                                    0,
                                    1,
                                    0,
                                    5,
                                    0,
                                    0,
                                    1
                                ],
                                "visible": false
                            },
                            {
                                "type": "Sprite",
                                "name": "o0:f2:e0",
                                "matrix": [
                                    1,
                                    0,
                                    0,
                                    0,
                                    0,
                                    1,
                                    0,
                                    0,
                                    0,
                                    0,
                                    1,
                                    0,
                                    10,
                                    0,
                                    5,
                                    1
                                ],
                                "visible": false
                            },
                            {
                                "type": "Sprite",
                                "name": "o0:f2:e1",
                                "matrix": [
                                    1,
                                    0,
                                    0,
                                    0,
                                    0,
                                    1,
                                    0,
                                    0,
                                    0,
                                    0,
                                    1,
                                    0,
                                    10,
                                    5,
                                    10,
                                    1
                                ],
                                "visible": false
                            },
                            {
                                "type": "Sprite",
                                "name": "o0:f2:e2",
                                "matrix": [
                                    1,
                                    0,
                                    0,
                                    0,
                                    0,
                                    1,
                                    0,
                                    0,
                                    0,
                                    0,
                                    1,
                                    0,
                                    10,
                                    10,
                                    5,
                                    1
                                ],
                                "visible": false
                            },
                            {
                                "type": "Sprite",
                                "name": "o0:f2:e3",
                                "matrix": [
                                    1,
                                    0,
                                    0,
                                    0,
                                    0,
                                    1,
                                    0,
                                    0,
                                    0,
                                    0,
                                    1,
                                    0,
                                    10,
                                    5,
                                    0,
                                    1
                                ],
                                "visible": false
                            },
                            {
                                "type": "Sprite",
                                "name": "o0:f3:e0",
                                "matrix": [
                                    1,
                                    0,
                                    0,
                                    0,
                                    0,
                                    1,
                                    0,
                                    0,
                                    0,
                                    0,
                                    1,
                                    0,
                                    10,
                                    10,
                                    5,
                                    1
                                ],
                                "visible": false
                            },
                            {
                                "type": "Sprite",
                                "name": "o0:f3:e1",
                                "matrix": [
                                    1,
                                    0,
                                    0,
                                    0,
                                    0,
                                    1,
                                    0,
                                    0,
                                    0,
                                    0,
                                    1,
                                    0,
                                    5,
                                    10,
                                    10,
                                    1
                                ],
                                "visible": false
                            },
                            {
                                "type": "Sprite",
                                "name": "o0:f3:e2",
                                "matrix": [
                                    1,
                                    0,
                                    0,
                                    0,
                                    0,
                                    1,
                                    0,
                                    0,
                                    0,
                                    0,
                                    1,
                                    0,
                                    0,
                                    10,
                                    5,
                                    1
                                ],
                                "visible": false
                            },
                            {
                                "type": "Sprite",
                                "name": "o0:f3:e3",
                                "matrix": [
                                    1,
                                    0,
                                    0,
                                    0,
                                    0,
                                    1,
                                    0,
                                    0,
                                    0,
                                    0,
                                    1,
                                    0,
                                    5,
                                    10,
                                    0,
                                    1
                                ],
                                "visible": false
                            },
                            {
                                "type": "Sprite",
                                "name": "o0:f4:e0",
                                "matrix": [
                                    1,
                                    0,
                                    0,
                                    0,
                                    0,
                                    1,
                                    0,
                                    0,
                                    0,
                                    0,
                                    1,
                                    0,
                                    0,
                                    10,
                                    5,
                                    1
                                ],
                                "visible": false
                            },
                            {
                                "type": "Sprite",
                                "name": "o0:f4:e1",
                                "matrix": [
                                    1,
                                    0,
                                    0,
                                    0,
                                    0,
                                    1,
                                    0,
                                    0,
                                    0,
                                    0,
                                    1,
                                    0,
                                    0,
                                    5,
                                    10,
                                    1
                                ],
                                "visible": false
                            },
                            {
                                "type": "Sprite",
                                "name": "o0:f4:e2",
                                "matrix": [
                                    1,
                                    0,
                                    0,
                                    0,
                                    0,
                                    1,
                                    0,
                                    0,
                                    0,
                                    0,
                                    1,
                                    0,
                                    0,
                                    0,
                                    5,
                                    1
                                ],
                                "visible": false
                            },
                            {
                                "type": "Sprite",
                                "name": "o0:f4:e3",
                                "matrix": [
                                    1,
                                    0,
                                    0,
                                    0,
                                    0,
                                    1,
                                    0,
                                    0,
                                    0,
                                    0,
                                    1,
                                    0,
                                    0,
                                    5,
                                    0,
                                    1
                                ],
                                "visible": false
                            },
                            {
                                "type": "Sprite",
                                "name": "o0:f5:e0",
                                "matrix": [
                                    1,
                                    0,
                                    0,
                                    0,
                                    0,
                                    1,
                                    0,
                                    0,
                                    0,
                                    0,
                                    1,
                                    0,
                                    5,
                                    10,
                                    10,
                                    1
                                ],
                                "visible": false
                            },
                            {
                                "type": "Sprite",
                                "name": "o0:f5:e1",
                                "matrix": [
                                    1,
                                    0,
                                    0,
                                    0,
                                    0,
                                    1,
                                    0,
                                    0,
                                    0,
                                    0,
                                    1,
                                    0,
                                    10,
                                    5,
                                    10,
                                    1
                                ],
                                "visible": false
                            },
                            {
                                "type": "Sprite",
                                "name": "o0:f5:e2",
                                "matrix": [
                                    1,
                                    0,
                                    0,
                                    0,
                                    0,
                                    1,
                                    0,
                                    0,
                                    0,
                                    0,
                                    1,
                                    0,
                                    5,
                                    0,
                                    10,
                                    1
                                ],
                                "visible": false
                            },
                            {
                                "type": "Sprite",
                                "name": "o0:f5:e3",
                                "matrix": [
                                    1,
                                    0,
                                    0,
                                    0,
                                    0,
                                    1,
                                    0,
                                    0,
                                    0,
                                    0,
                                    1,
                                    0,
                                    0,
                                    5,
                                    10,
                                    1
                                ],
                                "visible": false
                            }
                        ]
                    },
                    {
                        "uuid": "aa134957-9f46-4b37-8d2d-230f3889133d",
                        "type": "Group",
                        "name": "Wires",
                        "children": []
                    },
                    {
                        "uuid": "cf678539-18b8-4719-9de2-886ae2df4502",
                        "type": "Group",
                        "name": "Faces",
                        "children": [
                            {
                                "type": "Sprite",
                                "name": "o0:f0",
                                "matrix": [
                                    1,
                                    0,
                                    0,
                                    0,
                                    0,
                                    1,
                                    0,
                                    0,
                                    0,
                                    0,
                                    1,
                                    0,
                                    5,
                                    5,
                                    0,
                                    1
                                ],
                                "visible": false
                            },
                            {
                                "type": "Sprite",
                                "name": "o0:f1",
                                "matrix": [
                                    1,
                                    0,
                                    0,
                                    0,
                                    0,
                                    1,
                                    0,
                                    0,
                                    0,
                                    0,
                                    1,
                                    0,
                                    5,
                                    0,
                                    5,
                                    1
                                ],
                                "visible": false
                            },
                            {
                                "type": "Sprite",
                                "name": "o0:f2",
                                "matrix": [
                                    1,
                                    0,
                                    0,
                                    0,
                                    0,
                                    1,
                                    0,
                                    0,
                                    0,
                                    0,
                                    1,
                                    0,
                                    10,
                                    5,
                                    5,
                                    1
                                ],
                                "visible": false
                            },
                            {
                                "type": "Sprite",
                                "name": "o0:f3",
                                "matrix": [
                                    1,
                                    0,
                                    0,
                                    0,
                                    0,
                                    1,
                                    0,
                                    0,
                                    0,
                                    0,
                                    1,
                                    0,
                                    5,
                                    10,
                                    5,
                                    1
                                ],
                                "visible": false
                            },
                            {
                                "type": "Sprite",
                                "name": "o0:f4",
                                "matrix": [
                                    1,
                                    0,
                                    0,
                                    0,
                                    0,
                                    1,
                                    0,
                                    0,
                                    0,
                                    0,
                                    1,
                                    0,
                                    0,
                                    5,
                                    5,
                                    1
                                ],
                                "visible": false
                            },
                            {
                                "type": "Sprite",
                                "name": "o0:f5",
                                "matrix": [
                                    1,
                                    0,
                                    0,
                                    0,
                                    0,
                                    1,
                                    0,
                                    0,
                                    0,
                                    0,
                                    1,
                                    0,
                                    5,
                                    5,
                                    10,
                                    1
                                ],
                                "visible": false
                            }
                        ]
                    },
                    {
                        "uuid": "58b4cb74-aaa8-43e4-ac37-1a99e494a5e6",
                        "type": "Group",
                        "name": "Edges",
                        "children": [
                            {
                                "type": "Sprite",
                                "name": "o0",
                                "matrix": [
                                    1,
                                    0,
                                    0,
                                    0,
                                    0,
                                    1,
                                    0,
                                    0,
                                    0,
                                    0,
                                    1,
                                    0,
                                    5,
                                    5,
                                    5,
                                    1
                                ],
                                "visible": false
                            }
                        ]
                    }
                ]
            }
        ]
    }
}