{
    "metadata": {
        "version": 4.5,
        "type": "Object",
        "generator": "gs-json"
    },
    "geometries": [
        {
            "uuid": "7951b2bb-c2f4-4f58-bde7-7cb7b86092c8",
            "type": "BufferGeometry",
            "data": {
                "attributes": {
                    "position": {
                        "itemSize": 3,
                        "type": "Float32Array",
                        "array": [
                            0,
                            10,
                            0,
                            0,
                            0,
                            0,
                            0,
                            0,
                            10,
                            0,
                            10,
                            10,
                            10,
                            0,
                            0,
                            10,
                            10,
                            0,
                            10,
                            0,
                            10,
                            10,
                            10,
                            10
                        ],
                        "normalized": false
                    }
                },
                "index": {
                    "type": "Uint16Array",
                    "array": [
                        5,
                        0,
                        1,
                        1,
                        4,
                        5,
                        6,
                        4,
                        1,
                        1,
                        2,
                        6,
                        7,
                        5,
                        4,
                        4,
                        6,
                        7,
                        3,
                        0,
                        5,
                        5,
                        7,
                        3,
                        6,
                        2,
                        3,
                        3,
                        7,
                        6
                    ]
                }
            }
        },
        {
            "uuid": "e1b9a668-e3eb-4a6d-8226-68fd71e9ee25",
            "type": "BufferGeometry",
            "data": {
                "attributes": {
                    "position": {
                        "itemSize": 3,
                        "type": "Float32Array",
                        "array": [
                            0,
                            10,
                            0,
                            0,
                            0,
                            0,
                            0,
                            0,
                            10,
                            0,
                            10,
                            10,
                            10,
                            0,
                            0,
                            10,
                            10,
                            0,
                            10,
                            0,
                            10,
                            10,
                            10,
                            10
                        ],
                        "normalized": false
                    }
                },
                "index": {
                    "type": "Uint16Array",
                    "array": [
                        0,
                        1,
                        1,
                        2,
                        2,
                        3,
                        3,
                        0,
                        1,
                        4,
                        4,
                        5,
                        5,
                        0,
                        0,
                        1,
                        1,
                        2,
                        2,
                        6,
                        6,
                        4,
                        4,
                        1,
                        4,
                        6,
                        6,
                        7,
                        7,
                        5,
                        5,
                        4,
                        5,
                        7,
                        7,
                        3,
                        3,
                        0,
                        0,
                        5,
                        3,
                        7,
                        7,
                        6,
                        6,
                        2,
                        2,
                        3
                    ]
                }
            }
        },
        {
            "uuid": "90fe784d-822d-4e4b-bd77-cc912edac00f",
            "type": "BufferGeometry",
            "data": {
                "attributes": {
                    "position": {
                        "itemSize": 3,
                        "type": "Float32Array",
                        "array": [
                            0,
                            10,
                            0,
                            0,
                            0,
                            0,
                            0,
                            0,
                            10,
                            0,
                            10,
                            10,
                            10,
                            0,
                            0,
                            10,
                            10,
                            0,
                            10,
                            0,
                            10,
                            10,
                            10,
                            10
                        ],
                        "normalized": false
                    }
                },
                "index": {
                    "type": "Uint16Array",
                    "array": [
                        0,
                        1,
                        2,
                        3
                    ]
                }
            }
        },
        {
            "uuid": "c57b77b4-f475-4e95-acc8-8b6a55477f06",
            "type": "BufferGeometry",
            "data": {
                "attributes": {
                    "position": {
                        "itemSize": 3,
                        "type": "Float32Array",
                        "array": [
                            0,
                            0,
                            0,
                            10,
                            0,
                            0,
                            10,
                            10,
                            0,
                            0,
                            10,
                            0,
                            0,
                            0,
                            10,
                            10,
                            0,
                            10,
                            10,
                            10,
                            10,
                            0,
                            10,
                            10
                        ],
                        "normalized": false
                    }
                }
            }
        }
    ],
    "materials": [
        {
            "uuid": "df1e1c09-7758-4cc3-8f11-a8b6ca45af9d",
            "type": "LineBasicMaterial",
            "color": 0,
            "vertexColors": 0,
            "side": 2,
            "blending": 0,
            "depthFunc": 3,
            "depthTest": true,
            "depthWrite": true
        },
        {
            "uuid": "c859e97a-7eb5-4bad-b6de-31d3a3b0aaeb",
            "type": "LineBasicMaterial",
            "color": 255,
            "vertexColors": 0,
            "side": 2,
            "blending": 0,
            "depthFunc": 3,
            "depthTest": true,
            "depthWrite": true
        },
        {
            "uuid": "e47d7be3-9278-4878-9484-f51ec53eb9c3",
            "type": "MeshPhongMaterial",
            "color": 16777215,
            "emissive": 0,
            "specular": 16777215,
            "shininess": 10,
            "vertexColors": 0,
            "side": 2,
            "blending": 0,
            "depthFunc": 3,
            "depthTest": true,
            "depthWrite": true,
            "transparent": false,
            "wireframe": false,
            "flatShading": true
        },
        {
            "uuid": "87d6510c-52f4-4b65-99b2-d178f2179db5",
            "type": "MeshPhongMaterial",
            "color": 0,
            "emissive": 0,
            "specular": 16777215,
            "shininess": 40,
            "vertexColors": 0,
            "side": 1,
            "blending": 0,
            "depthFunc": 3,
            "depthTest": true,
            "depthWrite": true,
            "transparent": true,
            "opacity": 0.5,
            "wireframe": false,
            "flatShading": true
        },
        {
            "uuid": "d9928187-8c76-4dd6-ae91-25c49ef16f97",
            "type": "PointsMaterial",
            "color": 16777215,
            "size": 2,
            "sizeAttenuation": false
        }
    ],
    "object": {
        "type": "Scene",
        "name": "Scene",
        "children": [
            {
                "uuid": "cd19058a-4cf3-4814-85c0-e7504704dcee",
                "type": "Mesh",
                "name": "All faces",
                "geometry": "7951b2bb-c2f4-4f58-bde7-7cb7b86092c8",
                "material": "e47d7be3-9278-4878-9484-f51ec53eb9c3",
                "castShadow": true,
                "receiveShadow": true
            },
            {
                "uuid": "50e4a843-5fe6-4ae8-a74b-323756e1187b",
                "type": "LineSegments",
                "name": "All edges",
                "geometry": "e1b9a668-e3eb-4a6d-8226-68fd71e9ee25",
                "material": "df1e1c09-7758-4cc3-8f11-a8b6ca45af9d",
                "castShadow": false,
                "receiveShadow": false
            },
            {
                "uuid": "9a475624-b31d-4e40-a3c1-7e6426693676",
                "type": "LineSegments",
                "name": "All wires",
                "geometry": "90fe784d-822d-4e4b-bd77-cc912edac00f",
                "material": "c859e97a-7eb5-4bad-b6de-31d3a3b0aaeb",
                "castShadow": false,
                "receiveShadow": false
            },
            {
                "uuid": "9486509d-6e03-4d88-bd24-35cd2aa74a75",
                "type": "Points",
                "name": "All points",
                "geometry": "c57b77b4-f475-4e95-acc8-8b6a55477f06",
                "material": "d9928187-8c76-4dd6-ae91-25c49ef16f97",
                "castShadow": false,
                "receiveShadow": false
            }
        ]
    }
}