{
    "metadata": {
        "version": 4.5,
        "type": "Object",
        "generator": "gs-json"
    },
    "geometries": [
        {
            "uuid": "e835338c-9c78-4210-8e14-6265a1e036f6",
            "type": "BufferGeometry",
            "data": {
                "attributes": {
                    "position": {
                        "itemSize": 3,
                        "type": "Float32Array",
                        "array": [
                            10,
                            0,
                            0,
                            10,
                            10,
                            0,
                            10,
                            10,
                            10,
                            10,
                            0,
                            10,
                            0,
                            10,
                            0,
                            0,
                            0,
                            0,
                            0,
                            0,
                            10,
                            0,
                            10,
                            10
                        ],
                        "normalized": false
                    }
                },
                "index": {
                    "type": "Uint16Array",
                    "array": [
                        1,
                        4,
                        5,
                        5,
                        0,
                        1,
                        3,
                        0,
                        5,
                        5,
                        6,
                        3,
                        7,
                        4,
                        1,
                        1,
                        2,
                        7,
                        3,
                        6,
                        7,
                        7,
                        2,
                        3
                    ]
                }
            }
        },
        {
            "uuid": "0e83ba96-e592-49d9-9479-e041bd1df0c4",
            "type": "BufferGeometry",
            "data": {
                "attributes": {
                    "position": {
                        "itemSize": 3,
                        "type": "Float32Array",
                        "array": [
                            10,
                            0,
                            0,
                            10,
                            10,
                            0,
                            10,
                            10,
                            10,
                            10,
                            0,
                            10,
                            0,
                            10,
                            0,
                            0,
                            0,
                            0,
                            0,
                            0,
                            10,
                            0,
                            10,
                            10
                        ],
                        "normalized": false
                    }
                },
                "index": {
                    "type": "Uint16Array",
                    "array": [
                        0,
                        1,
                        1,
                        2,
                        2,
                        3,
                        3,
                        0,
                        4,
                        5,
                        5,
                        6,
                        6,
                        7,
                        7,
                        4
                    ]
                }
            }
        },
        {
            "uuid": "d9d4a9ad-d683-4fc0-8857-458c9d1abbfa",
            "type": "BufferGeometry",
            "data": {
                "attributes": {
                    "position": {
                        "itemSize": 3,
                        "type": "Float32Array",
                        "array": [
                            10,
                            0,
                            0,
                            10,
                            10,
                            0,
                            10,
                            10,
                            10,
                            10,
                            0,
                            10,
                            0,
                            10,
                            0,
                            0,
                            0,
                            0,
                            0,
                            0,
                            10,
                            0,
                            10,
                            10
                        ],
                        "normalized": false
                    }
                },
                "index": {
                    "type": "Uint16Array",
                    "array": [
                        0,
                        1,
                        1,
                        2,
                        2,
                        3,
                        3,
                        0,
                        4,
                        5,
                        5,
                        6,
                        6,
                        7,
                        7,
                        4,
                        5,
                        0,
                        0,
                        1,
                        1,
                        4,
                        4,
                        5,
                        5,
                        6,
                        6,
                        3,
                        3,
                        0,
                        0,
                        5,
                        1,
                        2,
                        2,
                        7,
                        7,
                        4,
                        4,
                        1,
                        7,
                        2,
                        2,
                        3,
                        3,
                        6,
                        6,
                        7
                    ]
                }
            }
        },
        {
            "uuid": "30dde390-dc65-47c4-98b7-9ddb991c1fba",
            "type": "BufferGeometry",
            "data": {
                "attributes": {
                    "position": {
                        "itemSize": 3,
                        "type": "Float32Array",
                        "array": [
                            10,
                            0,
                            0,
                            10,
                            10,
                            0,
                            10,
                            10,
                            10,
                            10,
                            0,
                            10,
                            0,
                            10,
                            0,
                            0,
                            0,
                            0,
                            0,
                            0,
                            10,
                            0,
                            10,
                            10
                        ],
                        "normalized": false
                    }
                },
                "index": {
                    "type": "Uint16Array",
                    "array": [
                        0,
                        1,
                        2,
                        3,
                        4,
                        5,
                        6,
                        7,
                        5,
                        0,
                        1,
                        4,
                        5,
                        6,
                        3,
                        0,
                        1,
                        2,
                        7,
                        4,
                        7,
                        2,
                        3,
                        6
                    ]
                }
            }
        },
        {
            "uuid": "4fb8f11e-58ce-49e9-bd98-30bec4f32759",
            "type": "BufferGeometry",
            "data": {
                "attributes": {
                    "position": {
                        "itemSize": 3,
                        "type": "Float32Array",
                        "array": [
                            0,
                            0,
                            0,
                            10,
                            0,
                            0,
                            10,
                            10,
                            0,
                            0,
                            10,
                            0,
                            0,
                            0,
                            10,
                            10,
                            0,
                            10,
                            10,
                            10,
                            10,
                            0,
                            10,
                            10
                        ],
                        "normalized": false
                    }
                },
                "index": {
                    "type": "Uint16Array",
                    "array": [
                        0,
                        1,
                        2,
                        3,
                        4,
                        5,
                        6,
                        7
                    ]
                }
            }
        },
        {
            "uuid": "2a38a462-70d3-4368-85e0-6aa8db7cf779",
            "type": "BufferGeometry",
            "data": {
                "attributes": {
                    "position": {
                        "itemSize": 3,
                        "type": "Float32Array",
                        "array": [],
                        "normalized": false
                    }
                },
                "index": {
                    "type": "Uint16Array",
                    "array": []
                }
            }
        }
    ],
    "materials": [
        {
            "uuid": "8c92b761-6a4d-406f-860e-f56204a172a4",
            "type": "LineBasicMaterial",
            "color": 0,
            "vertexColors": 0,
            "side": 2,
            "blending": 0,
            "depthFunc": 3,
            "depthTest": true,
            "depthWrite": true
        },
        {
            "uuid": "fce01899-1f58-4d9f-bb9c-bbbf72709099",
            "type": "LineBasicMaterial",
            "color": 255,
            "vertexColors": 0,
            "side": 2,
            "blending": 0,
            "depthFunc": 3,
            "depthTest": true,
            "depthWrite": true
        },
        {
            "uuid": "3a603b8d-dcba-4cd1-afcc-b1ff77d6390f",
            "type": "MeshPhongMaterial",
            "color": 16777215,
            "emissive": 0,
            "specular": 16777215,
            "shininess": 10,
            "vertexColors": 0,
            "side": 2,
            "blending": 0,
            "depthFunc": 3,
            "depthTest": true,
            "depthWrite": true,
            "transparent": false,
            "wireframe": false,
            "flatShading": true
        },
        {
            "uuid": "08583b89-e481-495a-bff1-2392eafe4f7b",
            "type": "MeshPhongMaterial",
            "color": 0,
            "emissive": 0,
            "specular": 16777215,
            "shininess": 40,
            "vertexColors": 0,
            "side": 1,
            "blending": 0,
            "depthFunc": 3,
            "depthTest": true,
            "depthWrite": true,
            "transparent": true,
            "opacity": 0.5,
            "wireframe": false,
            "flatShading": true
        },
        {
            "uuid": "bff18d20-ffc6-4919-8f59-5a6bdd285026",
            "type": "PointsMaterial",
            "color": 16777215,
            "size": 2,
            "sizeAttenuation": false
        }
    ],
    "object": {
        "type": "Scene",
        "name": "Scene",
        "children": [
            {
                "uuid": "ebbc083b-a252-49d5-b759-a3d26f229300",
                "type": "Mesh",
                "name": "All faces",
                "geometry": "e835338c-9c78-4210-8e14-6265a1e036f6",
                "material": "3a603b8d-dcba-4cd1-afcc-b1ff77d6390f",
                "castShadow": true,
                "receiveShadow": true
            },
            {
                "uuid": "9426b701-1230-4f54-9473-7180718c76a4",
                "type": "LineSegments",
                "name": "All wires",
                "geometry": "0e83ba96-e592-49d9-9479-e041bd1df0c4",
                "material": "fce01899-1f58-4d9f-bb9c-bbbf72709099",
                "castShadow": false,
                "receiveShadow": false
            },
            {
                "uuid": "d95f59ee-1497-4e33-b0c2-b68991f33f93",
                "type": "LineSegments",
                "name": "All edges",
                "geometry": "d9d4a9ad-d683-4fc0-8857-458c9d1abbfa",
                "material": "8c92b761-6a4d-406f-860e-f56204a172a4",
                "castShadow": false,
                "receiveShadow": false
            },
            {
                "uuid": "e5aeb85c-7801-47fe-a507-26359e80cbb3",
                "type": "Points",
                "name": "All vertices",
                "geometry": "30dde390-dc65-47c4-98b7-9ddb991c1fba",
                "material": "bff18d20-ffc6-4919-8f59-5a6bdd285026",
                "castShadow": false,
                "receiveShadow": false
            },
            {
                "uuid": "762e23b8-f79d-4eb7-b48f-588bbe11bc79",
                "type": "Points",
                "name": "All points",
                "geometry": "4fb8f11e-58ce-49e9-bd98-30bec4f32759",
                "material": "bff18d20-ffc6-4919-8f59-5a6bdd285026",
                "castShadow": false,
                "receiveShadow": false
            },
            {
                "uuid": "97b90767-3ae9-4be3-be65-25e2843879c5",
                "type": "LineSegments",
                "name": "Other lines",
                "geometry": "2a38a462-70d3-4368-85e0-6aa8db7cf779",
                "material": "8c92b761-6a4d-406f-860e-f56204a172a4",
                "castShadow": false,
                "receiveShadow": false
            }
        ]
    }
}